{
  "SchemaVersion": "2.4",
  "ToolVersion": "Rev2.5",
  "GeneratedUtc": "2026-06-01T05:44:40.8631293Z",
  "ClientName": "TestClient",
  "EngagementId": "M13-TEST2",
  "Assessor": "TestAssessor",
  "TenantId": "contoso.onmicrosoft.com",
  "ExecutiveRiskPosture": "Critical",
  "BaselineAvailable": false,
  "Files": {
    "Manifest": ".\\out\\20260531_224440\\entra-decommissioning-control-plane-run-manifest-20260531_224440.json",
    "BaselineComparisonCsv": null,
    "Json": ".\\out\\20260531_224440\\entra-decommissioning-control-plane-findings-20260531_224440.json",
    "RemediationPlan": ".\\out\\20260531_224440\\entra-decommissioning-control-plane-remediation-plan-20260531_224440.md",
    "Csv": ".\\out\\20260531_224440\\entra-decommissioning-control-plane-assessment-20260531_224440.csv",
    "BaselineComparisonJson": null,
    "Html": ".\\out\\20260531_224440\\entra-decommissioning-control-plane-report-20260531_224440.html"
  },
  "SafetyStatement": "Rev2.4 generated read-only reporting artifacts and did not modify tenant configuration."
}
